determinator/__init__.py
determinator/const.py
determinator/convert2rdf.py
determinator/convert2skos.py
determinator/determinator.py
determinator/importskos.py
determinator/types.py
determinator/utils.py
determinator/vocab.py
determinator-0.1.2.dist-info/AUTHORS.rst
determinator-0.1.2.dist-info/LICENSE
determinator-0.1.2.dist-info/METADATA
determinator-0.1.2.dist-info/WHEEL
determinator-0.1.2.dist-info/entry_points.txt
determinator-0.1.2.dist-info/top_level.txt
determinator-0.1.2.dist-info/RECORD
