Metadata-Version: 2.1
Name: determinator
Version: 0.1.2
Summary: Package for terminology management with TermBase eXchange (TBX)
Home-page: https://github.com/DeNederlandscheBank/determinator
Author: Willem Jan Willemse
Author-email: w.j.willemse@dnb.nl
License: MIT license
Keywords: determinator
Platform: UNKNOWN
Classifier: Development Status :: 2 - Pre-Alpha
Classifier: Intended Audience :: Developers
Classifier: License :: OSI Approved :: MIT License
Classifier: Natural Language :: English
Classifier: Programming Language :: Python :: 3
Classifier: Programming Language :: Python :: 3.6
Classifier: Programming Language :: Python :: 3.7
Classifier: Programming Language :: Python :: 3.8
Requires-Python: >=3.6
Requires-Dist: Click (>=7.0)
Requires-Dist: xlsxwriter
Requires-Dist: rdflib
